aio_panasonic_comfort_cloud/__init__.py
aio_panasonic_comfort_cloud/apiclient.py
aio_panasonic_comfort_cloud/ccappversion.py
aio_panasonic_comfort_cloud/changerequestbuilder.py
aio_panasonic_comfort_cloud/constants.py
aio_panasonic_comfort_cloud/exceptions.py
aio_panasonic_comfort_cloud/helpers.py
aio_panasonic_comfort_cloud/panasonicauthentication.py
aio_panasonic_comfort_cloud/panasonicdevice.py
aio_panasonic_comfort_cloud/panasonicrequestheader.py
aio_panasonic_comfort_cloud/panasonicsession.py
aio_panasonic_comfort_cloud/panasonicsettings.py
aio_panasonic_comfort_cloud/testdata.py
aio_panasonic_comfort_cloud-2025.5.1.dist-info/licenses/LICENSE
aio_panasonic_comfort_cloud-2025.5.1.dist-info/METADATA
aio_panasonic_comfort_cloud-2025.5.1.dist-info/WHEEL
aio_panasonic_comfort_cloud-2025.5.1.dist-info/top_level.txt
aio_panasonic_comfort_cloud-2025.5.1.dist-info/RECORD
