Metadata-Version: 2.4
Name: aio-panasonic-comfort-cloud
Version: 2025.5.1
Summary: Asynchronous Python library for Panasonic Comfort Cloud API
Author-email: Jimmy Everling <jimmy@sockless.tech>
License: MIT License
Project-URL: Homepage, https://github.com/sockless-coding/aio-panasonic-comfort-cloud
Project-URL: Repository, https://github.com/sockless-coding/aio-panasonic-comfort-cloud.git
Project-URL: Bug Tracker, https://github.com/sockless-coding/aio-panasonic-comfort-cloud/issues
Keywords: panasonic,comfort cloud
Classifier: Programming Language :: Python :: 3
Classifier: License :: OSI Approved :: MIT License
Classifier: Operating System :: OS Independent
Requires-Python: >=3.10
License-File: LICENSE
Requires-Dist: aiohttp
Requires-Dist: urllib3
Requires-Dist: bs4
Requires-Dist: aiofiles
Requires-Dist: packaging
Dynamic: license-file
